LICENSE
README.md
pyproject.toml
setup.cfg
setup.py
shunting_yard/__init__.py
shunting_yard/__main__.py
shunting_yard/constants.py
shunting_yard/rpn.py
shunting_yard/shunting_yard.py
shunting_yard/tokenize.py
shunting_yard.egg-info/PKG-INFO
shunting_yard.egg-info/SOURCES.txt
shunting_yard.egg-info/dependency_links.txt
shunting_yard.egg-info/top_level.txt
tests/test_compute.py
tests/test_rpn.py
tests/test_shunting_yard.py
tests/test_tokenize.py