Metadata-Version: 2.1
Name: shunting-yard
Version: 1.0.12
Summary: Compute any math expression
Home-page: https://www.github.com/charon25/ShuntingYard
Download-URL: https://github.com/charon25/ShuntingYard/archive/refs/tags/v1.0.12.tar.gz
Author: Paul 'charon25' Kern
License: MIT
Requires-Python: >=3.9
License-File: LICENSE
